createsuperuser/__init__.py
createsuperuser/apps.py
createsuperuser/models.py
createsuperuser/signals.py
createsuperuser/migrations/0001_initial.py
createsuperuser/migrations/__init__.py
django_createsuperuser_signal-0.0.1.dist-info/LICENSE
django_createsuperuser_signal-0.0.1.dist-info/METADATA
django_createsuperuser_signal-0.0.1.dist-info/WHEEL
django_createsuperuser_signal-0.0.1.dist-info/top_level.txt
django_createsuperuser_signal-0.0.1.dist-info/RECORD
